o2g/ODbL-1.0.txt
o2g/__init__.py
o2g/cli.py
o2g/web.py
o2g/gtfs/__init__.py
o2g/gtfs/gtfs_dummy.py
o2g/gtfs/gtfs_misc.py
o2g/gtfs/gtfs_writer.py
o2g/osm/__init__.py
o2g/osm/exporter.py
o2g/osm/models.py
o2g/osm/builders/__init__.py
o2g/osm/builders/agency_builder.py
o2g/osm/builders/route_builder.py
o2g/osm/builders/shape_builder.py
o2g/osm/builders/stations.md
o2g/osm/builders/stop_builder.py
o2g/osm/handlers/__init__.py
o2g/osm/handlers/node_handler.py
o2g/osm/handlers/relation_handler.py
o2g/osm/handlers/way_handler.py
o2g/tests/__init__.py
o2g/tests/test_validation.py
o2g-0.6.0.dist-info/entry_points.txt
o2g-0.6.0.dist-info/LICENSE
o2g-0.6.0.dist-info/WHEEL
o2g-0.6.0.dist-info/METADATA
o2g-0.6.0.dist-info/RECORD
