Metadata-Version: 2.1
Name: o2g
Version: 0.6.0
Summary: A simple tool to extract GTFS feed from OpenStreetMap.
Home-page: https://github.com/hiposfer/o2g
License: UNKNOWN
Keywords: osm gtfs
Author: Mehdi Sadeghi
Author-email: mehdi@mehdix.org
Requires-Python: >=3.5
Classifier: Development Status :: 4 - Beta
Classifier: Intended Audience :: Developers
Classifier: License :: OSI Approved :: MIT License
Classifier: Programming Language :: Python :: 3
Requires-Dist: osmium
Requires-Dist: pytest; extra == "test"
Requires-Dist: bottle; extra == "web"
Provides-Extra: test
Provides-Extra: web
